neuracore/__init__.py
neuracore/utils.py
neuracore/api/__init__.py
neuracore/api/core.py
neuracore/api/datasets.py
neuracore/api/endpoints.py
neuracore/api/globals.py
neuracore/api/logging.py
neuracore/api/orgs_fetch.py
neuracore/api/training.py
neuracore/core/__init__.py
neuracore/core/auth.py
neuracore/core/const.py
neuracore/core/endpoint.py
neuracore/core/exceptions.py
neuracore/core/get_latest_sync_point.py
neuracore/core/mjcf_to_urdf.py
neuracore/core/organizations.py
neuracore/core/robot.py
neuracore/core/cli/__init__.py
neuracore/core/cli/app.py
neuracore/core/cli/generate_api_key.py
neuracore/core/cli/get_user_confirmation.py
neuracore/core/cli/input_lock.py
neuracore/core/cli/launch_server.py
neuracore/core/cli/select_current_org.py
neuracore/core/config/__init__.py
neuracore/core/config/config_manager.py
neuracore/core/config/get_api_key.py
neuracore/core/config/get_current_org.py
neuracore/core/data/__init__.py
neuracore/core/data/cache_manager.py
neuracore/core/data/dataset.py
neuracore/core/data/recording.py
neuracore/core/data/synced_dataset.py
neuracore/core/data/synced_recording.py
neuracore/core/streaming/__init__.py
neuracore/core/streaming/base_sse_consumer.py
neuracore/core/streaming/data_stream.py
neuracore/core/streaming/event_loop_utils.py
neuracore/core/streaming/recording_state_manager.py
neuracore/core/streaming/bucket_uploaders/__init__.py
neuracore/core/streaming/bucket_uploaders/bucket_uploader.py
neuracore/core/streaming/bucket_uploaders/resumable_upload.py
neuracore/core/streaming/bucket_uploaders/streaming_file_uploader.py
neuracore/core/streaming/bucket_uploaders/streaming_video_uploader.py
neuracore/core/streaming/p2p/__init__.py
neuracore/core/streaming/p2p/base_p2p_connection_manager.py
neuracore/core/streaming/p2p/enabled_manager.py
neuracore/core/streaming/p2p/signalling_events_consumer.py
neuracore/core/streaming/p2p/stream_manager_orchestrator.py
neuracore/core/streaming/p2p/consumer/__init__.py
neuracore-7.13.0.dist-info/licenses/LICENSE
neuracore-7.13.0.dist-info/METADATA
neuracore-7.13.0.dist-info/WHEEL
neuracore-7.13.0.dist-info/entry_points.txt
neuracore-7.13.0.dist-info/top_level.txt
neuracore-7.13.0.dist-info/RECORD
