Metadata-Version: 2.4
Name: neuracore
Version: 7.13.0
Summary: Neuracore Client Library
Home-page: https://github.com/neuracoreai/neuracore
Author: Stephen James
Author-email: stephen@neuracore.com
Keywords: robotics machine-learning ai client-library
Classifier: Development Status :: 3 - Alpha
Classifier: Intended Audience :: Developers
Classifier: License :: OSI Approved :: MIT License
Classifier: Operating System :: OS Independent
Classifier: Programming Language :: Python :: 3
Classifier: Programming Language :: Python :: 3.10
Classifier: Programming Language :: Python :: 3.11
Requires-Python: >=3.10
License-File: LICENSE
Requires-Dist: numpy>=2.0.0
Requires-Dist: requests>=2.31.0
Requires-Dist: pillow>=10.0.0
Requires-Dist: pyyaml>=6.0.1
Requires-Dist: tqdm>=4.66.0
Requires-Dist: requests-oauthlib
Requires-Dist: pydantic>=2.10
Requires-Dist: av==14.2.0
Requires-Dist: aiortc
Requires-Dist: aiohttp-sse-client
Requires-Dist: numpy-stl
Requires-Dist: wget
Requires-Dist: uvicorn[standard]
Requires-Dist: fastapi
Requires-Dist: psutil
Requires-Dist: typer>=0.20.0
Requires-Dist: neuracore-types<5.0.0,>=4.3.0
Requires-Dist: ordered_set
Provides-Extra: examples
Requires-Dist: matplotlib>=3.3.0; extra == "examples"
Requires-Dist: mujoco==2.3.7; extra == "examples"
Requires-Dist: pyquaternion>=0.9.5; extra == "examples"
Provides-Extra: mjcf
Requires-Dist: mujoco>3; extra == "mjcf"
Provides-Extra: ml
Requires-Dist: torch; extra == "ml"
Requires-Dist: torchvision; extra == "ml"
Requires-Dist: transformers==4.57.3; extra == "ml"
Requires-Dist: huggingface-hub==0.36.0; extra == "ml"
Requires-Dist: diffusers==0.35.1; extra == "ml"
Requires-Dist: safetensors==0.6.2; extra == "ml"
Requires-Dist: einops; extra == "ml"
Requires-Dist: hydra-core>=1.3.0; extra == "ml"
Requires-Dist: tensorboard>=2; extra == "ml"
Requires-Dist: names-generator>=0.2.0; extra == "ml"
Provides-Extra: dev
Requires-Dist: pytest>=6.2.5; extra == "dev"
Requires-Dist: pytest-cov>=2.12.1; extra == "dev"
Requires-Dist: pytest-asyncio>=0.15.1; extra == "dev"
Requires-Dist: pytest-xdist; extra == "dev"
Requires-Dist: twine>=3.4.2; extra == "dev"
Requires-Dist: requests-mock>=1.9.3; extra == "dev"
Requires-Dist: pre-commit; extra == "dev"
Dynamic: author
Dynamic: author-email
Dynamic: classifier
Dynamic: description
Dynamic: description-content-type
Dynamic: home-page
Dynamic: keywords
Dynamic: license-file
Dynamic: provides-extra
Dynamic: requires-dist
Dynamic: requires-python
Dynamic: summary
